tinybear/__init__.py
tinybear/_paths.py
tinybear/csv_xls.py
tinybear/exceptions.py
tinybear/html/__init__.py
tinybear/html/from_docx.py
tinybear/html/validate_html.py
tinybear/json_toml_yaml.py
tinybear/txt.py
tinybear-0.3.1.dist-info/LICENSE
tinybear-0.3.1.dist-info/METADATA
tinybear-0.3.1.dist-info/WHEEL
tinybear-0.3.1.dist-info/RECORD
