Metadata-Version: 2.1
Name: tinybear
Version: 0.3.1
Summary: Where you don't need pandas yet. Tools to work with TXT, CSV, HTML, XLSX etc.
Author: Dmitry K
Author-email: 58207913+lemontree210@users.noreply.github.com
Requires-Python: >=3.9,<4.0
Classifier: Programming Language :: Python :: 3
Classifier: Programming Language :: Python :: 3.9
Classifier: Programming Language :: Python :: 3.10
Classifier: Programming Language :: Python :: 3.11
Requires-Dist: beautifulsoup4 (>=4.13.5,<5.0.0)
Requires-Dist: html5lib (>=1.1,<2.0)
Requires-Dist: mammoth (>=1.10.0,<2.0.0)
Requires-Dist: openpyxl (>=3.1.5,<4.0.0)
Requires-Dist: pyyaml (>=6.0.2,<7.0.0)
Requires-Dist: toml (>=0.10.2,<0.11.0)
Project-URL: Documentation, https://lemontree210.github.io/tinybear/
Project-URL: Homepage, https://github.com/lemontree210/tinybear
